{"moduleDefinition":{"range":[1,1,1,26],"value":{"type":"normal","normal":{"moduleName":{"range":[1,8,1,12],"value":["Main"]},"exposingList":{"range":[1,13,1,26],"value":{"type":"all","all":[1,23,1,25]}}}}},"imports":[{"range":[3,1,3,15],"value":{"moduleName":{"range":[3,8,3,15],"value":["Browser"]},"moduleAlias":null,"exposingList":null}},{"range":[4,1,4,28],"value":{"moduleName":{"range":[4,8,4,14],"value":["Footer"]},"moduleAlias":null,"exposingList":{"range":[4,15,4,28],"value":{"type":"all","all":[4,25,4,27]}}}},{"range":[5,1,5,28],"value":{"moduleName":{"range":[5,8,5,14],"value":["Header"]},"moduleAlias":null,"exposingList":{"range":[5,15,5,28],"value":{"type":"all","all":[5,25,5,27]}}}},{"range":[6,1,6,37],"value":{"moduleName":{"range":[6,8,6,23],"value":["Helpers","Helpers"]},"moduleAlias":null,"exposingList":{"range":[6,24,6,37],"value":{"type":"all","all":[6,34,6,36]}}}},{"range":[7,1,7,26],"value":{"moduleName":{"range":[7,8,7,12],"value":["Html"]},"moduleAlias":null,"exposingList":{"range":[7,13,7,26],"value":{"type":"all","all":[7,23,7,25]}}}},{"range":[8,1,8,37],"value":{"moduleName":{"range":[8,8,8,23],"value":["Html","Attributes"]},"moduleAlias":null,"exposingList":{"range":[8,24,8,37],"value":{"type":"all","all":[8,34,8,36]}}}},{"range":[9,1,9,38],"value":{"moduleName":{"range":[9,8,9,19],"value":["Html","Events"]},"moduleAlias":null,"exposingList":{"range":[9,20,9,38],"value":{"type":"explicit","explicit":[{"range":[9,30,9,37],"value":{"type":"function","function":{"name":"onClick"}}}]}}}},{"range":[10,1,10,29],"value":{"moduleName":{"range":[10,8,10,15],"value":["Message"]},"moduleAlias":null,"exposingList":{"range":[10,16,10,29],"value":{"type":"all","all":[10,26,10,28]}}}},{"range":[11,1,11,35],"value":{"moduleName":{"range":[11,8,11,21],"value":["Page","Announce"]},"moduleAlias":null,"exposingList":{"range":[11,22,11,35],"value":{"type":"all","all":[11,32,11,34]}}}},{"range":[12,1,12,31],"value":{"moduleName":{"range":[12,8,12,17],"value":["Page","Home"]},"moduleAlias":null,"exposingList":{"range":[12,18,12,31],"value":{"type":"all","all":[12,28,12,30]}}}},{"range":[13,1,13,33],"value":{"moduleName":{"range":[13,8,13,19],"value":["Page","Images"]},"moduleAlias":null,"exposingList":{"range":[13,20,13,33],"value":{"type":"all","all":[13,30,13,32]}}}},{"range":[14,1,14,34],"value":{"moduleName":{"range":[14,8,14,20],"value":["Page","Landing"]},"moduleAlias":null,"exposingList":{"range":[14,21,14,34],"value":{"type":"all","all":[14,31,14,33]}}}},{"range":[15,1,15,35],"value":{"moduleName":{"range":[15,8,15,21],"value":["Page","PageType"]},"moduleAlias":null,"exposingList":{"range":[15,22,15,35],"value":{"type":"all","all":[15,32,15,34]}}}},{"range":[16,1,16,33],"value":{"moduleName":{"range":[16,8,16,19],"value":["Page","SignIn"]},"moduleAlias":null,"exposingList":{"range":[16,20,16,33],"value":{"type":"all","all":[16,30,16,32]}}}},{"range":[17,1,17,40],"value":{"moduleName":{"range":[17,8,17,26],"value":["Page","SubscribeForm"]},"moduleAlias":null,"exposingList":{"range":[17,27,17,40],"value":{"type":"all","all":[17,37,17,39]}}}},{"range":[18,1,18,32],"value":{"moduleName":{"range":[18,8,18,18],"value":["Page","Tutos"]},"moduleAlias":null,"exposingList":{"range":[18,19,18,32],"value":{"type":"all","all":[18,29,18,31]}}}},{"range":[19,1,19,43],"value":{"moduleName":{"range":[19,8,19,15],"value":["Request"]},"moduleAlias":null,"exposingList":{"range":[19,16,19,43],"value":{"type":"explicit","explicit":[{"range":[19,26,19,42],"value":{"type":"function","function":{"name":"authenticateUser"}}}]}}}},{"range":[20,1,20,26],"value":{"moduleName":{"range":[20,8,20,12],"value":["User"]},"moduleAlias":null,"exposingList":{"range":[20,13,20,26],"value":{"type":"all","all":[20,23,20,25]}}}}],"declarations":[{"range":[23,1,30,6],"value":{"type":"typeAlias","typeAlias":{"documentation":null,"name":{"range":[23,12,23,17],"value":"Model"},"generics":[],"typeAnnotation":{"range":[24,5,30,6],"value":{"type":"record","record":{"value":[{"range":[24,7,24,18],"value":{"name":{"range":[24,7,24,11],"value":"page"},"typeAnnotation":{"range":[24,14,24,18],"value":{"type":"typed","typed":{"moduleNameAndName":{"range":[24,14,24,18],"value":{"moduleName":[],"name":"Page"}},"args":[]}}}}},{"range":[25,5,26,5],"value":{"name":{"range":[25,7,25,13],"value":"header"},"typeAnnotation":{"range":[25,16,25,22],"value":{"type":"typed","typed":{"moduleNameAndName":{"range":[25,16,25,22],"value":{"moduleName":[],"name":"Header"}},"args":[]}}}}},{"range":[26,5,27,5],"value":{"name":{"range":[26,7,26,13],"value":"footer"},"typeAnnotation":{"range":[26,16,26,22],"value":{"type":"typed","typed":{"moduleNameAndName":{"range":[26,16,26,22],"value":{"moduleName":[],"name":"Footer"}},"args":[]}}}}},{"range":[27,5,28,5],"value":{"name":{"range":[27,7,27,17],"value":"signupForm"},"typeAnnotation":{"range":[27,20,27,36],"value":{"type":"typed","typed":{"moduleNameAndName":{"range":[27,20,27,36],"value":{"moduleName":[],"name":"SubscriptionForm"}},"args":[]}}}}},{"range":[28,5,29,5],"value":{"name":{"range":[28,7,28,17],"value":"signinForm"},"typeAnnotation":{"range":[28,20,28,30],"value":{"type":"typed","typed":{"moduleNameAndName":{"range":[28,20,28,30],"value":{"moduleName":[],"name":"SignInForm"}},"args":[]}}}}},{"range":[29,5,30,5],"value":{"name":{"range":[29,7,29,18],"value":"userProfile"},"typeAnnotation":{"range":[29,21,29,32],"value":{"type":"typed","typed":{"moduleNameAndName":{"range":[29,21,29,32],"value":{"moduleName":[],"name":"UserProfile"}},"args":[]}}}}}]}}}}}},{"range":[33,1,40,10],"value":{"type":"function","function":{"documentation":null,"signature":{"range":[33,1,33,28],"value":{"name":{"range":[33,1,33,5],"value":"main"},"typeAnnotation":{"range":[33,8,33,28],"value":{"type":"typed","typed":{"moduleNameAndName":{"range":[33,8,33,15],"value":{"moduleName":[],"name":"Program"}},"args":[{"range":[33,16,33,18],"value":{"type":"unit","unit":{}}},{"range":[33,19,33,24],"value":{"type":"typed","typed":{"moduleNameAndName":{"range":[33,19,33,24],"value":{"moduleName":[],"name":"Model"}},"args":[]}}},{"range":[33,25,33,28],"value":{"type":"typed","typed":{"moduleNameAndName":{"range":[33,25,33,28],"value":{"moduleName":[],"name":"Msg"}},"args":[]}}}]}}}}},"declaration":{"range":[34,1,40,10],"value":{"name":{"range":[34,1,34,5],"value":"main"},"arguments":[],"expression":{"range":[35,5,40,10],"value":{"type":"application","application":[{"range":[35,5,35,20],"value":{"type":"functionOrValue","functionOrValue":{"moduleName":["Browser"],"name":"element"}}},{"range":[36,9,40,10],"value":{"type":"record","record":[{"range":[36,11,36,22],"value":{"field":{"range":[36,11,36,15],"value":"init"},"expression":{"range":[36,18,36,22],"value":{"type":"functionOrValue","functionOrValue":{"moduleName":[],"name":"init"}}}}},{"range":[37,11,38,9],"value":{"field":{"range":[37,11,37,15],"value":"view"},"expression":{"range":[37,18,37,22],"value":{"type":"functionOrValue","functionOrValue":{"moduleName":[],"name":"view"}}}}},{"range":[38,11,39,9],"value":{"field":{"range":[38,11,38,17],"value":"update"},"expression":{"range":[38,20,38,26],"value":{"type":"functionOrValue","functionOrValue":{"moduleName":[],"name":"update"}}}}},{"range":[39,11,40,9],"value":{"field":{"range":[39,11,39,24],"value":"subscriptions"},"expression":{"range":[39,27,40,9],"value":{"type":"lambda","lambda":{"patterns":[{"range":[39,28,39,29],"value":{"type":"all","all":{}}}],"expression":{"range":[39,33,39,41],"value":{"type":"functionOrValue","functionOrValue":{"moduleName":["Sub"],"name":"none"}}}}}}}}]}}]}}}}}}},{"range":[43,1,69,1],"value":{"type":"function","function":{"documentation":null,"signature":{"range":[43,1,43,32],"value":{"name":{"range":[43,1,43,5],"value":"init"},"typeAnnotation":{"range":[43,8,43,32],"value":{"type":"function","function":{"left":{"range":[43,8,43,10],"value":{"type":"unit","unit":{}}},"right":{"range":[43,14,43,32],"value":{"type":"tupled","tupled":{"values":[{"range":[43,16,43,21],"value":{"type":"typed","typed":{"moduleNameAndName":{"range":[43,16,43,21],"value":{"moduleName":[],"name":"Model"}},"args":[]}}},{"range":[43,23,43,30],"value":{"type":"typed","typed":{"moduleNameAndName":{"range":[43,23,43,26],"value":{"moduleName":[],"name":"Cmd"}},"args":[{"range":[43,27,43,30],"value":{"type":"typed","typed":{"moduleNameAndName":{"range":[43,27,43,30],"value":{"moduleName":[],"name":"Msg"}},"args":[]}}}]}}}]}}}}}}}},"declaration":{"range":[44,1,69,1],"value":{"name":{"range":[44,1,44,5],"value":"init"},"arguments":[{"range":[44,6,44,8],"value":{"type":"unit","unit":{}}}],"expression":{"range":[45,5,69,1],"value":{"type":"let","let":{"declarations":[{"range":[46,9,62,5],"value":{"type":"function","function":{"documentation":null,"signature":null,"declaration":{"range":[46,9,61,14],"value":{"name":{"range":[46,9,46,21],"value":"initialModel"},"arguments":[],"expression":{"range":[47,13,61,14],"value":{"type":"record","record":[{"range":[47,15,47,29],"value":{"field":{"range":[47,15,47,19],"value":"page"},"expression":{"range":[47,22,47,29],"value":{"type":"functionOrValue","functionOrValue":{"moduleName":[],"name":"Landing"}}}}},{"range":[48,15,49,13],"value":{"field":{"range":[48,15,48,21],"value":"header"},"expression":{"range":[48,24,48,33],"value":{"type":"functionOrValue","functionOrValue":{"moduleName":[],"name":"Connexion"}}}}},{"range":[49,15,50,13],"value":{"field":{"range":[49,15,49,21],"value":"footer"},"expression":{"range":[49,24,49,34],"value":{"type":"functionOrValue","functionOrValue":{"moduleName":[],"name":"ForLanding"}}}}},{"range":[50,15,56,13],"value":{"field":{"range":[50,15,50,25],"value":"signupForm"},"expression":{"range":[51,17,55,18],"value":{"type":"record","record":[{"range":[51,19,51,33],"value":{"field":{"range":[51,19,51,28],"value":"firstName"},"expression":{"range":[51,31,51,33],"value":{"type":"literal","literal":""}}}},{"range":[52,19,53,17],"value":{"field":{"range":[52,19,52,27],"value":"lastName"},"expression":{"range":[52,30,52,32],"value":{"type":"literal","literal":""}}}},{"range":[53,19,54,17],"value":{"field":{"range":[53,19,53,24],"value":"class"},"expression":{"range":[53,27,53,29],"value":{"type":"literal","literal":""}}}},{"range":[54,19,55,17],"value":{"field":{"range":[54,19,54,23],"value":"mail"},"expression":{"range":[54,26,54,28],"value":{"type":"literal","literal":""}}}}]}}}},{"range":[56,15,60,13],"value":{"field":{"range":[56,15,56,25],"value":"signinForm"},"expression":{"range":[57,17,59,18],"value":{"type":"record","record":[{"range":[57,19,57,32],"value":{"field":{"range":[57,19,57,27],"value":"username"},"expression":{"range":[57,30,57,32],"value":{"type":"literal","literal":""}}}},{"range":[58,19,59,17],"value":{"field":{"range":[58,19,58,22],"value":"pwd"},"expression":{"range":[58,25,58,27],"value":{"type":"literal","literal":""}}}}]}}}},{"range":[60,15,61,13],"value":{"field":{"range":[60,15,60,26],"value":"userProfile"},"expression":{"range":[60,29,60,35],"value":{"type":"functionOrValue","functionOrValue":{"moduleName":[],"name":"NotSet"}}}}}]}}}}}}}],"expression":{"range":[63,5,63,31],"value":{"type":"tupled","tupled":[{"range":[63,7,63,19],"value":{"type":"functionOrValue","functionOrValue":{"moduleName":[],"name":"initialModel"}}},{"range":[63,21,63,29],"value":{"type":"functionOrValue","functionOrValue":{"moduleName":["Cmd"],"name":"none"}}}]}}}}}}}}}},{"range":[69,1,71,61],"value":{"type":"function","function":{"documentation":null,"signature":{"range":[69,1,69,25],"value":{"name":{"range":[69,1,69,5],"value":"view"},"typeAnnotation":{"range":[69,8,69,25],"value":{"type":"function","function":{"left":{"range":[69,8,69,13],"value":{"type":"typed","typed":{"moduleNameAndName":{"range":[69,8,69,13],"value":{"moduleName":[],"name":"Model"}},"args":[]}}},"right":{"range":[69,17,69,25],"value":{"type":"typed","typed":{"moduleNameAndName":{"range":[69,17,69,21],"value":{"moduleName":[],"name":"Html"}},"args":[{"range":[69,22,69,25],"value":{"type":"typed","typed":{"moduleNameAndName":{"range":[69,22,69,25],"value":{"moduleName":[],"name":"Msg"}},"args":[]}}}]}}}}}}}},"declaration":{"range":[70,1,71,61],"value":{"name":{"range":[70,1,70,5],"value":"view"},"arguments":[{"range":[70,6,70,11],"value":{"type":"var","var":{"value":"model"}}}],"expression":{"range":[71,5,71,61],"value":{"type":"application","application":[{"range":[71,5,71,8],"value":{"type":"functionOrValue","functionOrValue":{"moduleName":[],"name":"div"}}},{"range":[71,9,71,44],"value":{"type":"list","list":[{"range":[71,11,71,42],"value":{"type":"application","application":[{"range":[71,11,71,32],"value":{"type":"functionOrValue","functionOrValue":{"moduleName":["Html","Attributes"],"name":"class"}}},{"range":[71,33,71,42],"value":{"type":"literal","literal":"wrapper"}}]}}]}},{"range":[71,45,71,61],"value":{"type":"parenthesized","parenthesized":{"range":[71,46,71,60],"value":{"type":"application","application":[{"range":[71,46,71,54],"value":{"type":"functionOrValue","functionOrValue":{"moduleName":[],"name":"viewPage"}}},{"range":[71,55,71,60],"value":{"type":"functionOrValue","functionOrValue":{"moduleName":[],"name":"model"}}}]}}}}]}}}}}}},{"range":[74,1,79,6],"value":{"type":"function","function":{"documentation":null,"signature":{"range":[74,1,74,36],"value":{"name":{"range":[74,1,74,9],"value":"viewPage"},"typeAnnotation":{"range":[74,12,74,36],"value":{"type":"function","function":{"left":{"range":[74,12,74,17],"value":{"type":"typed","typed":{"moduleNameAndName":{"range":[74,12,74,17],"value":{"moduleName":[],"name":"Model"}},"args":[]}}},"right":{"range":[74,21,74,36],"value":{"type":"typed","typed":{"moduleNameAndName":{"range":[74,21,74,25],"value":{"moduleName":[],"name":"List"}},"args":[{"range":[74,26,74,36],"value":{"type":"typed","typed":{"moduleNameAndName":{"range":[74,27,74,31],"value":{"moduleName":[],"name":"Html"}},"args":[{"range":[74,32,74,35],"value":{"type":"typed","typed":{"moduleNameAndName":{"range":[74,32,74,35],"value":{"moduleName":[],"name":"Msg"}},"args":[]}}}]}}}]}}}}}}}},"declaration":{"range":[75,1,79,6],"value":{"name":{"range":[75,1,75,9],"value":"viewPage"},"arguments":[{"range":[75,10,75,15],"value":{"type":"var","var":{"value":"model"}}}],"expression":{"range":[76,5,79,6],"value":{"type":"list","list":[{"range":[76,7,76,23],"value":{"type":"application","application":[{"range":[76,7,76,17],"value":{"type":"functionOrValue","functionOrValue":{"moduleName":[],"name":"viewHeader"}}},{"range":[76,18,76,23],"value":{"type":"functionOrValue","functionOrValue":{"moduleName":[],"name":"model"}}}]}},{"range":[77,7,77,21],"value":{"type":"application","application":[{"range":[77,7,77,15],"value":{"type":"functionOrValue","functionOrValue":{"moduleName":[],"name":"viewMain"}}},{"range":[77,16,77,21],"value":{"type":"functionOrValue","functionOrValue":{"moduleName":[],"name":"model"}}}]}},{"range":[78,7,78,23],"value":{"type":"application","application":[{"range":[78,7,78,17],"value":{"type":"functionOrValue","functionOrValue":{"moduleName":[],"name":"viewFooter"}}},{"range":[78,18,78,23],"value":{"type":"functionOrValue","functionOrValue":{"moduleName":[],"name":"model"}}}]}}]}}}}}}},{"range":[82,1,89,71],"value":{"type":"function","function":{"documentation":null,"signature":{"range":[82,1,82,31],"value":{"name":{"range":[82,1,82,11],"value":"viewHeader"},"typeAnnotation":{"range":[82,14,82,31],"value":{"type":"function","function":{"left":{"range":[82,14,82,19],"value":{"type":"typed","typed":{"moduleNameAndName":{"range":[82,14,82,19],"value":{"moduleName":[],"name":"Model"}},"args":[]}}},"right":{"range":[82,23,82,31],"value":{"type":"typed","typed":{"moduleNameAndName":{"range":[82,23,82,27],"value":{"moduleName":[],"name":"Html"}},"args":[{"range":[82,28,82,31],"value":{"type":"typed","typed":{"moduleNameAndName":{"range":[82,28,82,31],"value":{"moduleName":[],"name":"Msg"}},"args":[]}}}]}}}}}}}},"declaration":{"range":[83,1,89,71],"value":{"name":{"range":[83,1,83,11],"value":"viewHeader"},"arguments":[{"range":[83,12,83,17],"value":{"type":"var","var":{"value":"model"}}}],"expression":{"range":[84,5,89,71],"value":{"type":"case","case":{"cases":[{"pattern":{"range":[85,9,85,18],"value":{"type":"named","named":{"qualified":{"moduleName":[],"name":"Connexion"},"patterns":[]}}},"expression":{"range":[86,13,86,70],"value":{"type":"application","application":[{"range":[86,13,86,19],"value":{"type":"functionOrValue","functionOrValue":{"moduleName":[],"name":"header"}}},{"range":[86,20,86,22],"value":{"type":"list","list":[]}},{"range":[86,23,86,70],"value":{"type":"parenthesized","parenthesized":{"range":[86,24,86,69],"value":{"type":"application","application":[{"range":[86,24,86,41],"value":{"type":"functionOrValue","functionOrValue":{"moduleName":[],"name":"viewElemntsHeader"}}},{"range":[86,42,86,51],"value":{"type":"functionOrValue","functionOrValue":{"moduleName":[],"name":"Connexion"}}},{"range":[86,57,86,69],"value":{"type":"recordAccess","recordAccess":{"expression":{"range":[86,52,86,57],"value":{"type":"functionOrValue","functionOrValue":{"moduleName":[],"name":"model"}}},"name":{"range":[86,58,86,69],"value":"userProfile"}}}}]}}}}]}}},{"pattern":{"range":[88,9,88,19],"value":{"type":"named","named":{"qualified":{"moduleName":[],"name":"Identified"},"patterns":[]}}},"expression":{"range":[89,13,89,71],"value":{"type":"application","application":[{"range":[89,13,89,19],"value":{"type":"functionOrValue","functionOrValue":{"moduleName":[],"name":"header"}}},{"range":[89,20,89,22],"value":{"type":"list","list":[]}},{"range":[89,23,89,71],"value":{"type":"parenthesized","parenthesized":{"range":[89,24,89,70],"value":{"type":"application","application":[{"range":[89,24,89,41],"value":{"type":"functionOrValue","functionOrValue":{"moduleName":[],"name":"viewElemntsHeader"}}},{"range":[89,42,89,52],"value":{"type":"functionOrValue","functionOrValue":{"moduleName":[],"name":"Identified"}}},{"range":[89,58,89,70],"value":{"type":"recordAccess","recordAccess":{"expression":{"range":[89,53,89,58],"value":{"type":"functionOrValue","functionOrValue":{"moduleName":[],"name":"model"}}},"name":{"range":[89,59,89,70],"value":"userProfile"}}}}]}}}}]}}}],"expression":{"range":[84,15,84,22],"value":{"type":"recordAccess","recordAccess":{"expression":{"range":[84,10,84,15],"value":{"type":"functionOrValue","functionOrValue":{"moduleName":[],"name":"model"}}},"name":{"range":[84,16,84,22],"value":"header"}}}}}}}}}}}},{"range":[92,1,114,41],"value":{"type":"function","function":{"documentation":null,"signature":{"range":[92,1,92,29],"value":{"name":{"range":[92,1,92,9],"value":"viewMain"},"typeAnnotation":{"range":[92,12,92,29],"value":{"type":"function","function":{"left":{"range":[92,12,92,17],"value":{"type":"typed","typed":{"moduleNameAndName":{"range":[92,12,92,17],"value":{"moduleName":[],"name":"Model"}},"args":[]}}},"right":{"range":[92,21,92,29],"value":{"type":"typed","typed":{"moduleNameAndName":{"range":[92,21,92,25],"value":{"moduleName":[],"name":"Html"}},"args":[{"range":[92,26,92,29],"value":{"type":"typed","typed":{"moduleNameAndName":{"range":[92,26,92,29],"value":{"moduleName":[],"name":"Msg"}},"args":[]}}}]}}}}}}}},"declaration":{"range":[93,1,114,41],"value":{"name":{"range":[93,1,93,9],"value":"viewMain"},"arguments":[{"range":[93,10,93,15],"value":{"type":"var","var":{"value":"model"}}}],"expression":{"range":[94,5,114,41],"value":{"type":"case","case":{"cases":[{"pattern":{"range":[95,9,95,16],"value":{"type":"named","named":{"qualified":{"moduleName":[],"name":"Landing"},"patterns":[]}}},"expression":{"range":[96,13,96,35],"value":{"type":"application","application":[{"range":[96,13,96,23],"value":{"type":"functionOrValue","functionOrValue":{"moduleName":["Html"],"name":"main_"}}},{"range":[96,24,96,26],"value":{"type":"list","list":[]}},{"range":[96,27,96,35],"value":{"type":"functionOrValue","functionOrValue":{"moduleName":[],"name":"viewLogo"}}}]}}},{"pattern":{"range":[98,9,98,28],"value":{"type":"named","named":{"qualified":{"moduleName":[],"name":"Announcement"},"patterns":[{"range":[98,22,98,28],"value":{"type":"var","var":{"value":"blocks"}}}]}}},"expression":{"range":[99,13,99,46],"value":{"type":"application","application":[{"range":[99,13,99,23],"value":{"type":"functionOrValue","functionOrValue":{"moduleName":["Html"],"name":"main_"}}},{"range":[99,24,99,26],"value":{"type":"list","list":[]}},{"range":[99,27,99,46],"value":{"type":"parenthesized","parenthesized":{"range":[99,28,99,45],"value":{"type":"application","application":[{"range":[99,28,99,38],"value":{"type":"functionOrValue","functionOrValue":{"moduleName":[],"name":"viewBlocks"}}},{"range":[99,39,99,45],"value":{"type":"functionOrValue","functionOrValue":{"moduleName":[],"name":"blocks"}}}]}}}}]}}},{"pattern":{"range":[101,9,101,13],"value":{"type":"named","named":{"qualified":{"moduleName":[],"name":"Home"},"patterns":[]}}},"expression":{"range":[102,13,102,35],"value":{"type":"application","application":[{"range":[102,13,102,23],"value":{"type":"functionOrValue","functionOrValue":{"moduleName":["Html"],"name":"main_"}}},{"range":[102,24,102,26],"value":{"type":"list","list":[]}},{"range":[102,27,102,35],"value":{"type":"functionOrValue","functionOrValue":{"moduleName":[],"name":"viewNews"}}}]}}},{"pattern":{"range":[104,9,104,18],"value":{"type":"named","named":{"qualified":{"moduleName":[],"name":"Subscribe"},"patterns":[]}}},"expression":{"range":[105,13,105,54],"value":{"type":"application","application":[{"range":[105,13,105,23],"value":{"type":"functionOrValue","functionOrValue":{"moduleName":["Html"],"name":"main_"}}},{"range":[105,24,105,26],"value":{"type":"list","list":[]}},{"range":[105,27,105,54],"value":{"type":"parenthesized","parenthesized":{"range":[105,28,105,53],"value":{"type":"application","application":[{"range":[105,28,105,36],"value":{"type":"functionOrValue","functionOrValue":{"moduleName":[],"name":"viewForm"}}},{"range":[105,42,105,53],"value":{"type":"recordAccess","recordAccess":{"expression":{"range":[105,37,105,42],"value":{"type":"functionOrValue","functionOrValue":{"moduleName":[],"name":"model"}}},"name":{"range":[105,43,105,53],"value":"signupForm"}}}}]}}}}]}}},{"pattern":{"range":[107,9,107,15],"value":{"type":"named","named":{"qualified":{"moduleName":[],"name":"SignIn"},"patterns":[]}}},"expression":{"range":[108,13,108,110],"value":{"type":"application","application":[{"range":[108,13,108,23],"value":{"type":"functionOrValue","functionOrValue":{"moduleName":["Html"],"name":"main_"}}},{"range":[108,24,108,62],"value":{"type":"list","list":[{"range":[108,26,108,60],"value":{"type":"application","application":[{"range":[108,26,108,47],"value":{"type":"functionOrValue","functionOrValue":{"moduleName":["Html","Attributes"],"name":"class"}}},{"range":[108,48,108,60],"value":{"type":"literal","literal":"signinPage"}}]}}]}},{"range":[108,63,108,110],"value":{"type":"parenthesized","parenthesized":{"range":[108,64,108,109],"value":{"type":"application","application":[{"range":[108,64,108,74],"value":{"type":"functionOrValue","functionOrValue":{"moduleName":[],"name":"viewSignIn"}}},{"range":[108,80,108,91],"value":{"type":"recordAccess","recordAccess":{"expression":{"range":[108,75,108,80],"value":{"type":"functionOrValue","functionOrValue":{"moduleName":[],"name":"model"}}},"name":{"range":[108,81,108,91],"value":"signinForm"}}}},{"range":[108,97,108,109],"value":{"type":"recordAccess","recordAccess":{"expression":{"range":[108,92,108,97],"value":{"type":"functionOrValue","functionOrValue":{"moduleName":[],"name":"model"}}},"name":{"range":[108,98,108,109],"value":"userProfile"}}}}]}}}}]}}},{"pattern":{"range":[110,9,110,14],"value":{"type":"named","named":{"qualified":{"moduleName":[],"name":"Tutos"},"patterns":[]}}},"expression":{"range":[111,13,111,40],"value":{"type":"application","application":[{"range":[111,13,111,23],"value":{"type":"functionOrValue","functionOrValue":{"moduleName":["Html"],"name":"main_"}}},{"range":[111,24,111,26],"value":{"type":"list","list":[]}},{"range":[111,27,111,40],"value":{"type":"list","list":[{"range":[111,29,111,38],"value":{"type":"functionOrValue","functionOrValue":{"moduleName":[],"name":"viewTutos"}}}]}}]}}},{"pattern":{"range":[113,9,113,15],"value":{"type":"named","named":{"qualified":{"moduleName":[],"name":"Images"},"patterns":[]}}},"expression":{"range":[114,13,114,41],"value":{"type":"application","application":[{"range":[114,13,114,23],"value":{"type":"functionOrValue","functionOrValue":{"moduleName":["Html"],"name":"main_"}}},{"range":[114,24,114,26],"value":{"type":"list","list":[]}},{"range":[114,27,114,41],"value":{"type":"list","list":[{"range":[114,29,114,39],"value":{"type":"functionOrValue","functionOrValue":{"moduleName":[],"name":"viewImages"}}}]}}]}}}],"expression":{"range":[94,15,94,20],"value":{"type":"recordAccess","recordAccess":{"expression":{"range":[94,10,94,15],"value":{"type":"functionOrValue","functionOrValue":{"moduleName":[],"name":"model"}}},"name":{"range":[94,16,94,20],"value":"page"}}}}}}}}}}}},{"range":[117,1,164,18],"value":{"type":"function","function":{"documentation":null,"signature":{"range":[117,1,117,31],"value":{"name":{"range":[117,1,117,11],"value":"viewFooter"},"typeAnnotation":{"range":[117,14,117,31],"value":{"type":"function","function":{"left":{"range":[117,14,117,19],"value":{"type":"typed","typed":{"moduleNameAndName":{"range":[117,14,117,19],"value":{"moduleName":[],"name":"Model"}},"args":[]}}},"right":{"range":[117,23,117,31],"value":{"type":"typed","typed":{"moduleNameAndName":{"range":[117,23,117,27],"value":{"moduleName":[],"name":"Html"}},"args":[{"range":[117,28,117,31],"value":{"type":"typed","typed":{"moduleNameAndName":{"range":[117,28,117,31],"value":{"moduleName":[],"name":"Msg"}},"args":[]}}}]}}}}}}}},"declaration":{"range":[118,1,164,18],"value":{"name":{"range":[118,1,118,11],"value":"viewFooter"},"arguments":[{"range":[118,12,118,17],"value":{"type":"var","var":{"value":"model"}}}],"expression":{"range":[119,5,164,18],"value":{"type":"case","case":{"cases":[{"pattern":{"range":[120,9,120,21],"value":{"type":"named","named":{"qualified":{"moduleName":[],"name":"Presentation"},"patterns":[]}}},"expression":{"range":[121,13,129,18],"value":{"type":"application","application":[{"range":[121,13,121,19],"value":{"type":"functionOrValue","functionOrValue":{"moduleName":[],"name":"footer"}}},{"range":[121,20,121,22],"value":{"type":"list","list":[]}},{"range":[122,17,129,18],"value":{"type":"list","list":[{"range":[122,19,127,22],"value":{"type":"application","application":[{"range":[122,19,122,22],"value":{"type":"functionOrValue","functionOrValue":{"moduleName":[],"name":"div"}}},{"range":[122,23,122,60],"value":{"type":"list","list":[{"range":[122,25,122,58],"value":{"type":"application","application":[{"range":[122,25,122,46],"value":{"type":"functionOrValue","functionOrValue":{"moduleName":["Html","Attributes"],"name":"class"}}},{"range":[122,47,122,58],"value":{"type":"literal","literal":"container"}}]}}]}},{"range":[123,21,127,22],"value":{"type":"list","list":[{"range":[123,23,123,103],"value":{"type":"application","application":[{"range":[123,23,123,29],"value":{"type":"functionOrValue","functionOrValue":{"moduleName":[],"name":"button"}}},{"range":[123,30,123,75],"value":{"type":"list","list":[{"range":[123,32,123,59],"value":{"type":"application","application":[{"range":[123,32,123,53],"value":{"type":"functionOrValue","functionOrValue":{"moduleName":["Html","Attributes"],"name":"class"}}},{"range":[123,54,123,59],"value":{"type":"literal","literal":"nav"}}]}},{"range":[123,61,123,73],"value":{"type":"application","application":[{"range":[123,61,123,68],"value":{"type":"functionOrValue","functionOrValue":{"moduleName":[],"name":"onClick"}}},{"range":[123,69,123,73],"value":{"type":"functionOrValue","functionOrValue":{"moduleName":[],"name":"What"}}}]}}]}},{"range":[123,76,123,103],"value":{"type":"list","list":[{"range":[123,78,123,101],"value":{"type":"application","application":[{"range":[123,78,123,87],"value":{"type":"functionOrValue","functionOrValue":{"moduleName":["Html"],"name":"text"}}},{"range":[123,88,123,101],"value":{"type":"literal","literal":"C'est quoi?"}}]}}]}}]}},{"range":[124,23,124,109],"value":{"type":"application","application":[{"range":[124,23,124,29],"value":{"type":"functionOrValue","functionOrValue":{"moduleName":[],"name":"button"}}},{"range":[124,30,124,79],"value":{"type":"list","list":[{"range":[124,32,124,59],"value":{"type":"application","application":[{"range":[124,32,124,53],"value":{"type":"functionOrValue","functionOrValue":{"moduleName":["Html","Attributes"],"name":"class"}}},{"range":[124,54,124,59],"value":{"type":"literal","literal":"nav"}}]}},{"range":[124,61,124,77],"value":{"type":"application","application":[{"range":[124,61,124,68],"value":{"type":"functionOrValue","functionOrValue":{"moduleName":[],"name":"onClick"}}},{"range":[124,69,124,77],"value":{"type":"functionOrValue","functionOrValue":{"moduleName":[],"name":"WhatToDo"}}}]}}]}},{"range":[124,80,124,109],"value":{"type":"list","list":[{"range":[124,82,124,107],"value":{"type":"application","application":[{"range":[124,82,124,91],"value":{"type":"functionOrValue","functionOrValue":{"moduleName":["Html"],"name":"text"}}},{"range":[124,92,124,107],"value":{"type":"literal","literal":"On fait quoi?"}}]}}]}}]}},{"range":[125,23,125,107],"value":{"type":"application","application":[{"range":[125,23,125,29],"value":{"type":"functionOrValue","functionOrValue":{"moduleName":[],"name":"button"}}},{"range":[125,30,125,77],"value":{"type":"list","list":[{"range":[125,32,125,59],"value":{"type":"application","application":[{"range":[125,32,125,53],"value":{"type":"functionOrValue","functionOrValue":{"moduleName":["Html","Attributes"],"name":"class"}}},{"range":[125,54,125,59],"value":{"type":"literal","literal":"nav"}}]}},{"range":[125,61,125,75],"value":{"type":"application","application":[{"range":[125,61,125,68],"value":{"type":"functionOrValue","functionOrValue":{"moduleName":[],"name":"onClick"}}},{"range":[125,69,125,75],"value":{"type":"functionOrValue","functionOrValue":{"moduleName":[],"name":"SignUp"}}}]}}]}},{"range":[125,78,125,107],"value":{"type":"list","list":[{"range":[125,80,125,105],"value":{"type":"application","application":[{"range":[125,80,125,89],"value":{"type":"functionOrValue","functionOrValue":{"moduleName":["Html"],"name":"text"}}},{"range":[125,90,125,105],"value":{"type":"literal","literal":"Je m'inscris!"}}]}}]}}]}},{"range":[126,23,126,110],"value":{"type":"application","application":[{"range":[126,23,126,29],"value":{"type":"functionOrValue","functionOrValue":{"moduleName":[],"name":"button"}}},{"range":[126,30,126,75],"value":{"type":"list","list":[{"range":[126,32,126,59],"value":{"type":"application","application":[{"range":[126,32,126,53],"value":{"type":"functionOrValue","functionOrValue":{"moduleName":["Html","Attributes"],"name":"class"}}},{"range":[126,54,126,59],"value":{"type":"literal","literal":"nav"}}]}},{"range":[126,61,126,73],"value":{"type":"application","application":[{"range":[126,61,126,68],"value":{"type":"functionOrValue","functionOrValue":{"moduleName":[],"name":"onClick"}}},{"range":[126,69,126,73],"value":{"type":"functionOrValue","functionOrValue":{"moduleName":[],"name":"When"}}}]}}]}},{"range":[126,76,126,110],"value":{"type":"list","list":[{"range":[126,78,126,108],"value":{"type":"application","application":[{"range":[126,78,126,87],"value":{"type":"functionOrValue","functionOrValue":{"moduleName":["Html"],"name":"text"}}},{"range":[126,88,126,108],"value":{"type":"literal","literal":"On commence quand?"}}]}}]}}]}}]}}]}},{"range":[128,19,128,25],"value":{"type":"functionOrValue","functionOrValue":{"moduleName":[],"name":"gitHub"}}}]}}]}}},{"pattern":{"range":[131,9,131,13],"value":{"type":"named","named":{"qualified":{"moduleName":[],"name":"Bare"},"patterns":[]}}},"expression":{"range":[132,13,136,18],"value":{"type":"application","application":[{"range":[132,13,132,19],"value":{"type":"functionOrValue","functionOrValue":{"moduleName":[],"name":"footer"}}},{"range":[132,20,132,22],"value":{"type":"list","list":[]}},{"range":[133,17,136,18],"value":{"type":"list","list":[{"range":[133,19,134,23],"value":{"type":"application","application":[{"range":[133,19,133,22],"value":{"type":"functionOrValue","functionOrValue":{"moduleName":[],"name":"div"}}},{"range":[133,23,133,60],"value":{"type":"list","list":[{"range":[133,25,133,58],"value":{"type":"application","application":[{"range":[133,25,133,46],"value":{"type":"functionOrValue","functionOrValue":{"moduleName":["Html","Attributes"],"name":"class"}}},{"range":[133,47,133,58],"value":{"type":"literal","literal":"container"}}]}}]}},{"range":[134,21,134,23],"value":{"type":"list","list":[]}}]}},{"range":[135,19,135,25],"value":{"type":"functionOrValue","functionOrValue":{"moduleName":[],"name":"gitHub"}}}]}}]}}},{"pattern":{"range":[138,9,138,12],"value":{"type":"named","named":{"qualified":{"moduleName":[],"name":"Nav"},"patterns":[]}}},"expression":{"range":[139,13,143,18],"value":{"type":"application","application":[{"range":[139,13,139,19],"value":{"type":"functionOrValue","functionOrValue":{"moduleName":[],"name":"footer"}}},{"range":[139,20,139,22],"value":{"type":"list","list":[]}},{"range":[140,17,143,18],"value":{"type":"list","list":[{"range":[140,19,141,102],"value":{"type":"application","application":[{"range":[140,19,140,22],"value":{"type":"functionOrValue","functionOrValue":{"moduleName":[],"name":"div"}}},{"range":[140,23,140,60],"value":{"type":"list","list":[{"range":[140,25,140,58],"value":{"type":"application","application":[{"range":[140,25,140,46],"value":{"type":"functionOrValue","functionOrValue":{"moduleName":["Html","Attributes"],"name":"class"}}},{"range":[140,47,140,58],"value":{"type":"literal","literal":"container"}}]}}]}},{"range":[141,21,141,102],"value":{"type":"list","list":[{"range":[141,23,141,100],"value":{"type":"application","application":[{"range":[141,23,141,29],"value":{"type":"functionOrValue","functionOrValue":{"moduleName":[],"name":"button"}}},{"range":[141,30,141,78],"value":{"type":"list","list":[{"range":[141,32,141,59],"value":{"type":"application","application":[{"range":[141,32,141,53],"value":{"type":"functionOrValue","functionOrValue":{"moduleName":["Html","Attributes"],"name":"class"}}},{"range":[141,54,141,59],"value":{"type":"literal","literal":"nav"}}]}},{"range":[141,61,141,76],"value":{"type":"application","application":[{"range":[141,61,141,68],"value":{"type":"functionOrValue","functionOrValue":{"moduleName":[],"name":"onClick"}}},{"range":[141,69,141,76],"value":{"type":"functionOrValue","functionOrValue":{"moduleName":[],"name":"ToTutos"}}}]}}]}},{"range":[141,79,141,100],"value":{"type":"list","list":[{"range":[141,81,141,98],"value":{"type":"application","application":[{"range":[141,81,141,90],"value":{"type":"functionOrValue","functionOrValue":{"moduleName":["Html"],"name":"text"}}},{"range":[141,91,141,98],"value":{"type":"literal","literal":"Tutos"}}]}}]}}]}}]}}]}},{"range":[142,19,142,25],"value":{"type":"functionOrValue","functionOrValue":{"moduleName":[],"name":"gitHub"}}}]}}]}}},{"pattern":{"range":[145,9,145,19],"value":{"type":"named","named":{"qualified":{"moduleName":[],"name":"ForLanding"},"patterns":[]}}},"expression":{"range":[146,13,146,22],"value":{"type":"application","application":[{"range":[146,13,146,16],"value":{"type":"functionOrValue","functionOrValue":{"moduleName":[],"name":"div"}}},{"range":[146,17,146,19],"value":{"type":"list","list":[]}},{"range":[146,20,146,22],"value":{"type":"list","list":[]}}]}}},{"pattern":{"range":[148,9,148,17],"value":{"type":"named","named":{"qualified":{"moduleName":[],"name":"ForTutos"},"patterns":[]}}},"expression":{"range":[149,13,155,18],"value":{"type":"application","application":[{"range":[149,13,149,19],"value":{"type":"functionOrValue","functionOrValue":{"moduleName":[],"name":"footer"}}},{"range":[149,20,149,22],"value":{"type":"list","list":[]}},{"range":[150,17,155,18],"value":{"type":"list","list":[{"range":[150,19,153,22],"value":{"type":"application","application":[{"range":[150,19,150,22],"value":{"type":"functionOrValue","functionOrValue":{"moduleName":[],"name":"div"}}},{"range":[150,23,150,60],"value":{"type":"list","list":[{"range":[150,25,150,58],"value":{"type":"application","application":[{"range":[150,25,150,46],"value":{"type":"functionOrValue","functionOrValue":{"moduleName":["Html","Attributes"],"name":"class"}}},{"range":[150,47,150,58],"value":{"type":"literal","literal":"container"}}]}}]}},{"range":[151,21,153,22],"value":{"type":"list","list":[{"range":[151,23,151,124],"value":{"type":"application","application":[{"range":[151,23,151,27],"value":{"type":"functionOrValue","functionOrValue":{"moduleName":[],"name":"text"}}},{"range":[151,28,151,124],"value":{"type":"literal","literal":"<<Attention>> Les Tutos les plus anciens sont en fin page! Le plus récent apparaît en premier."}}]}},{"range":[152,23,152,104],"value":{"type":"application","application":[{"range":[152,23,152,29],"value":{"type":"functionOrValue","functionOrValue":{"moduleName":[],"name":"button"}}},{"range":[152,30,152,81],"value":{"type":"list","list":[{"range":[152,32,152,59],"value":{"type":"application","application":[{"range":[152,32,152,53],"value":{"type":"functionOrValue","functionOrValue":{"moduleName":["Html","Attributes"],"name":"class"}}},{"range":[152,54,152,59],"value":{"type":"literal","literal":"nav"}}]}},{"range":[152,61,152,79],"value":{"type":"application","application":[{"range":[152,61,152,68],"value":{"type":"functionOrValue","functionOrValue":{"moduleName":[],"name":"onClick"}}},{"range":[152,69,152,79],"value":{"type":"functionOrValue","functionOrValue":{"moduleName":[],"name":"ToPictures"}}}]}}]}},{"range":[152,82,152,104],"value":{"type":"list","list":[{"range":[152,84,152,102],"value":{"type":"application","application":[{"range":[152,84,152,93],"value":{"type":"functionOrValue","functionOrValue":{"moduleName":["Html"],"name":"text"}}},{"range":[152,94,152,102],"value":{"type":"literal","literal":"Images"}}]}}]}}]}}]}}]}},{"range":[154,19,154,25],"value":{"type":"functionOrValue","functionOrValue":{"moduleName":[],"name":"gitHub"}}}]}}]}}},{"pattern":{"range":[157,9,157,18],"value":{"type":"named","named":{"qualified":{"moduleName":[],"name":"ForImages"},"patterns":[]}}},"expression":{"range":[158,13,164,18],"value":{"type":"application","application":[{"range":[158,13,158,19],"value":{"type":"functionOrValue","functionOrValue":{"moduleName":[],"name":"footer"}}},{"range":[158,20,158,22],"value":{"type":"list","list":[]}},{"range":[159,17,164,18],"value":{"type":"list","list":[{"range":[159,19,162,22],"value":{"type":"application","application":[{"range":[159,19,159,22],"value":{"type":"functionOrValue","functionOrValue":{"moduleName":[],"name":"div"}}},{"range":[159,23,159,60],"value":{"type":"list","list":[{"range":[159,25,159,58],"value":{"type":"application","application":[{"range":[159,25,159,46],"value":{"type":"functionOrValue","functionOrValue":{"moduleName":["Html","Attributes"],"name":"class"}}},{"range":[159,47,159,58],"value":{"type":"literal","literal":"container"}}]}}]}},{"range":[160,21,162,22],"value":{"type":"list","list":[{"range":[160,23,160,117],"value":{"type":"application","application":[{"range":[160,23,160,27],"value":{"type":"functionOrValue","functionOrValue":{"moduleName":[],"name":"text"}}},{"range":[160,28,160,117],"value":{"type":"literal","literal":"Ces images sont indispensables pour réussir certains exercices proposés dans les tutos."}}]}},{"range":[161,23,161,100],"value":{"type":"application","application":[{"range":[161,23,161,29],"value":{"type":"functionOrValue","functionOrValue":{"moduleName":[],"name":"button"}}},{"range":[161,30,161,78],"value":{"type":"list","list":[{"range":[161,32,161,59],"value":{"type":"application","application":[{"range":[161,32,161,53],"value":{"type":"functionOrValue","functionOrValue":{"moduleName":["Html","Attributes"],"name":"class"}}},{"range":[161,54,161,59],"value":{"type":"literal","literal":"nav"}}]}},{"range":[161,61,161,76],"value":{"type":"application","application":[{"range":[161,61,161,68],"value":{"type":"functionOrValue","functionOrValue":{"moduleName":[],"name":"onClick"}}},{"range":[161,69,161,76],"value":{"type":"functionOrValue","functionOrValue":{"moduleName":[],"name":"ToTutos"}}}]}}]}},{"range":[161,79,161,100],"value":{"type":"list","list":[{"range":[161,81,161,98],"value":{"type":"application","application":[{"range":[161,81,161,90],"value":{"type":"functionOrValue","functionOrValue":{"moduleName":["Html"],"name":"text"}}},{"range":[161,91,161,98],"value":{"type":"literal","literal":"Tutos"}}]}}]}}]}}]}}]}},{"range":[163,19,163,25],"value":{"type":"functionOrValue","functionOrValue":{"moduleName":[],"name":"gitHub"}}}]}}]}}}],"expression":{"range":[119,15,119,22],"value":{"type":"recordAccess","recordAccess":{"expression":{"range":[119,10,119,15],"value":{"type":"functionOrValue","functionOrValue":{"moduleName":[],"name":"model"}}},"name":{"range":[119,16,119,22],"value":"footer"}}}}}}}}}}}},{"range":[167,1,224,85],"value":{"type":"function","function":{"documentation":null,"signature":{"range":[167,1,167,44],"value":{"name":{"range":[167,1,167,7],"value":"update"},"typeAnnotation":{"range":[167,10,167,44],"value":{"type":"function","function":{"left":{"range":[167,10,167,13],"value":{"type":"typed","typed":{"moduleNameAndName":{"range":[167,10,167,13],"value":{"moduleName":[],"name":"Msg"}},"args":[]}}},"right":{"range":[167,17,167,44],"value":{"type":"function","function":{"left":{"range":[167,17,167,22],"value":{"type":"typed","typed":{"moduleNameAndName":{"range":[167,17,167,22],"value":{"moduleName":[],"name":"Model"}},"args":[]}}},"right":{"range":[167,26,167,44],"value":{"type":"tupled","tupled":{"values":[{"range":[167,28,167,33],"value":{"type":"typed","typed":{"moduleNameAndName":{"range":[167,28,167,33],"value":{"moduleName":[],"name":"Model"}},"args":[]}}},{"range":[167,35,167,42],"value":{"type":"typed","typed":{"moduleNameAndName":{"range":[167,35,167,38],"value":{"moduleName":[],"name":"Cmd"}},"args":[{"range":[167,39,167,42],"value":{"type":"typed","typed":{"moduleNameAndName":{"range":[167,39,167,42],"value":{"moduleName":[],"name":"Msg"}},"args":[]}}}]}}}]}}}}}}}}}}},"declaration":{"range":[168,1,224,85],"value":{"name":{"range":[168,1,168,7],"value":"update"},"arguments":[{"range":[168,8,168,11],"value":{"type":"var","var":{"value":"msg"}}},{"range":[168,12,168,17],"value":{"type":"var","var":{"value":"model"}}}],"expression":{"range":[169,5,224,85],"value":{"type":"case","case":{"cases":[{"pattern":{"range":[170,9,170,17],"value":{"type":"named","named":{"qualified":{"moduleName":[],"name":"BackHome"},"patterns":[]}}},"expression":{"range":[171,13,171,64],"value":{"type":"tupled","tupled":[{"range":[171,15,171,52],"value":{"type":"recordUpdate","recordUpdate":{"name":{"range":[171,17,171,22],"value":"model"},"updates":[{"range":[171,25,171,36],"value":{"field":{"range":[171,25,171,29],"value":"page"},"expression":{"range":[171,32,171,36],"value":{"type":"functionOrValue","functionOrValue":{"moduleName":[],"name":"Home"}}}}},{"range":[171,38,171,51],"value":{"field":{"range":[171,38,171,44],"value":"footer"},"expression":{"range":[171,47,171,50],"value":{"type":"functionOrValue","functionOrValue":{"moduleName":[],"name":"Nav"}}}}}]}}},{"range":[171,54,171,62],"value":{"type":"functionOrValue","functionOrValue":{"moduleName":["Cmd"],"name":"none"}}}]}}},{"pattern":{"range":[173,9,173,17],"value":{"type":"named","named":{"qualified":{"moduleName":[],"name":"Announce"},"patterns":[]}}},"expression":{"range":[174,13,174,62],"value":{"type":"tupled","tupled":[{"range":[174,15,174,50],"value":{"type":"recordUpdate","recordUpdate":{"name":{"range":[174,17,174,22],"value":"model"},"updates":[{"range":[174,25,174,49],"value":{"field":{"range":[174,25,174,29],"value":"page"},"expression":{"range":[174,32,174,48],"value":{"type":"application","application":[{"range":[174,32,174,44],"value":{"type":"functionOrValue","functionOrValue":{"moduleName":[],"name":"Announcement"}}},{"range":[174,45,174,48],"value":{"type":"functionOrValue","functionOrValue":{"moduleName":[],"name":"New"}}}]}}}}]}}},{"range":[174,52,174,60],"value":{"type":"functionOrValue","functionOrValue":{"moduleName":["Cmd"],"name":"none"}}}]}}},{"pattern":{"range":[176,9,176,13],"value":{"type":"named","named":{"qualified":{"moduleName":[],"name":"What"},"patterns":[]}}},"expression":{"range":[177,13,177,67],"value":{"type":"tupled","tupled":[{"range":[177,15,177,55],"value":{"type":"recordUpdate","recordUpdate":{"name":{"range":[177,17,177,22],"value":"model"},"updates":[{"range":[177,25,177,54],"value":{"field":{"range":[177,25,177,29],"value":"page"},"expression":{"range":[177,32,177,53],"value":{"type":"application","application":[{"range":[177,32,177,44],"value":{"type":"functionOrValue","functionOrValue":{"moduleName":[],"name":"Announcement"}}},{"range":[177,45,177,53],"value":{"type":"functionOrValue","functionOrValue":{"moduleName":[],"name":"WhatIsIt"}}}]}}}}]}}},{"range":[177,57,177,65],"value":{"type":"functionOrValue","functionOrValue":{"moduleName":["Cmd"],"name":"none"}}}]}}},{"pattern":{"range":[179,9,179,13],"value":{"type":"named","named":{"qualified":{"moduleName":[],"name":"When"},"patterns":[]}}},"expression":{"range":[180,13,180,72],"value":{"type":"tupled","tupled":[{"range":[180,15,180,60],"value":{"type":"recordUpdate","recordUpdate":{"name":{"range":[180,17,180,22],"value":"model"},"updates":[{"range":[180,25,180,59],"value":{"field":{"range":[180,25,180,29],"value":"page"},"expression":{"range":[180,32,180,58],"value":{"type":"application","application":[{"range":[180,32,180,44],"value":{"type":"functionOrValue","functionOrValue":{"moduleName":[],"name":"Announcement"}}},{"range":[180,45,180,58],"value":{"type":"functionOrValue","functionOrValue":{"moduleName":[],"name":"WhenDoWeStart"}}}]}}}}]}}},{"range":[180,62,180,70],"value":{"type":"functionOrValue","functionOrValue":{"moduleName":["Cmd"],"name":"none"}}}]}}},{"pattern":{"range":[182,9,182,17],"value":{"type":"named","named":{"qualified":{"moduleName":[],"name":"WhatToDo"},"patterns":[]}}},"expression":{"range":[183,13,183,69],"value":{"type":"tupled","tupled":[{"range":[183,15,183,57],"value":{"type":"recordUpdate","recordUpdate":{"name":{"range":[183,17,183,22],"value":"model"},"updates":[{"range":[183,25,183,56],"value":{"field":{"range":[183,25,183,29],"value":"page"},"expression":{"range":[183,32,183,55],"value":{"type":"application","application":[{"range":[183,32,183,44],"value":{"type":"functionOrValue","functionOrValue":{"moduleName":[],"name":"Announcement"}}},{"range":[183,45,183,55],"value":{"type":"functionOrValue","functionOrValue":{"moduleName":[],"name":"WhatDoWeDo"}}}]}}}}]}}},{"range":[183,59,183,67],"value":{"type":"functionOrValue","functionOrValue":{"moduleName":["Cmd"],"name":"none"}}}]}}},{"pattern":{"range":[185,9,185,15],"value":{"type":"named","named":{"qualified":{"moduleName":[],"name":"SignUp"},"patterns":[]}}},"expression":{"range":[186,13,186,55],"value":{"type":"tupled","tupled":[{"range":[186,15,186,43],"value":{"type":"recordUpdate","recordUpdate":{"name":{"range":[186,17,186,22],"value":"model"},"updates":[{"range":[186,25,186,42],"value":{"field":{"range":[186,25,186,29],"value":"page"},"expression":{"range":[186,32,186,41],"value":{"type":"functionOrValue","functionOrValue":{"moduleName":[],"name":"Subscribe"}}}}}]}}},{"range":[186,45,186,53],"value":{"type":"functionOrValue","functionOrValue":{"moduleName":["Cmd"],"name":"none"}}}]}}},{"pattern":{"range":[188,9,188,16],"value":{"type":"named","named":{"qualified":{"moduleName":[],"name":"ToTutos"},"patterns":[]}}},"expression":{"range":[189,13,189,70],"value":{"type":"tupled","tupled":[{"range":[189,15,189,58],"value":{"type":"recordUpdate","recordUpdate":{"name":{"range":[189,17,189,22],"value":"model"},"updates":[{"range":[189,25,189,37],"value":{"field":{"range":[189,25,189,29],"value":"page"},"expression":{"range":[189,32,189,37],"value":{"type":"functionOrValue","functionOrValue":{"moduleName":[],"name":"Tutos"}}}}},{"range":[189,39,189,57],"value":{"field":{"range":[189,39,189,45],"value":"footer"},"expression":{"range":[189,48,189,56],"value":{"type":"functionOrValue","functionOrValue":{"moduleName":[],"name":"ForTutos"}}}}}]}}},{"range":[189,60,189,68],"value":{"type":"functionOrValue","functionOrValue":{"moduleName":["Cmd"],"name":"none"}}}]}}},{"pattern":{"range":[191,9,191,19],"value":{"type":"named","named":{"qualified":{"moduleName":[],"name":"ToPictures"},"patterns":[]}}},"expression":{"range":[192,13,192,72],"value":{"type":"tupled","tupled":[{"range":[192,15,192,60],"value":{"type":"recordUpdate","recordUpdate":{"name":{"range":[192,17,192,22],"value":"model"},"updates":[{"range":[192,25,192,38],"value":{"field":{"range":[192,25,192,29],"value":"page"},"expression":{"range":[192,32,192,38],"value":{"type":"functionOrValue","functionOrValue":{"moduleName":[],"name":"Images"}}}}},{"range":[192,40,192,59],"value":{"field":{"range":[192,40,192,46],"value":"footer"},"expression":{"range":[192,49,192,58],"value":{"type":"functionOrValue","functionOrValue":{"moduleName":[],"name":"ForImages"}}}}}]}}},{"range":[192,62,192,70],"value":{"type":"functionOrValue","functionOrValue":{"moduleName":["Cmd"],"name":"none"}}}]}}},{"pattern":{"range":[194,9,194,23],"value":{"type":"named","named":{"qualified":{"moduleName":[],"name":"Authentication"},"patterns":[]}}},"expression":{"range":[195,13,195,52],"value":{"type":"tupled","tupled":[{"range":[195,15,195,40],"value":{"type":"recordUpdate","recordUpdate":{"name":{"range":[195,17,195,22],"value":"model"},"updates":[{"range":[195,25,195,39],"value":{"field":{"range":[195,25,195,29],"value":"page"},"expression":{"range":[195,32,195,38],"value":{"type":"functionOrValue","functionOrValue":{"moduleName":[],"name":"SignIn"}}}}}]}}},{"range":[195,42,195,50],"value":{"type":"functionOrValue","functionOrValue":{"moduleName":["Cmd"],"name":"none"}}}]}}},{"pattern":{"range":[197,9,197,30],"value":{"type":"named","named":{"qualified":{"moduleName":[],"name":"GotUserProfile"},"patterns":[{"range":[197,24,197,30],"value":{"type":"var","var":{"value":"result"}}}]}}},"expression":{"range":[198,13,203,83],"value":{"type":"case","case":{"cases":[{"pattern":{"range":[199,17,199,29],"value":{"type":"named","named":{"qualified":{"moduleName":[],"name":"Ok"},"patterns":[{"range":[199,20,199,29],"value":{"type":"var","var":{"value":"userInfos"}}}]}}},"expression":{"range":[200,21,200,122],"value":{"type":"tupled","tupled":[{"range":[200,23,200,110],"value":{"type":"recordUpdate","recordUpdate":{"name":{"range":[200,25,200,30],"value":"model"},"updates":[{"range":[200,33,200,44],"value":{"field":{"range":[200,33,200,37],"value":"page"},"expression":{"range":[200,40,200,44],"value":{"type":"functionOrValue","functionOrValue":{"moduleName":[],"name":"Home"}}}}},{"range":[200,46,200,65],"value":{"field":{"range":[200,46,200,52],"value":"header"},"expression":{"range":[200,55,200,65],"value":{"type":"functionOrValue","functionOrValue":{"moduleName":[],"name":"Identified"}}}}},{"range":[200,67,200,79],"value":{"field":{"range":[200,67,200,73],"value":"footer"},"expression":{"range":[200,76,200,79],"value":{"type":"functionOrValue","functionOrValue":{"moduleName":[],"name":"Nav"}}}}},{"range":[200,81,200,109],"value":{"field":{"range":[200,81,200,92],"value":"userProfile"},"expression":{"range":[200,95,200,108],"value":{"type":"application","application":[{"range":[200,95,200,98],"value":{"type":"functionOrValue","functionOrValue":{"moduleName":[],"name":"Set"}}},{"range":[200,99,200,108],"value":{"type":"functionOrValue","functionOrValue":{"moduleName":[],"name":"userInfos"}}}]}}}}]}}},{"range":[200,112,200,120],"value":{"type":"functionOrValue","functionOrValue":{"moduleName":["Cmd"],"name":"none"}}}]}}},{"pattern":{"range":[202,17,202,22],"value":{"type":"named","named":{"qualified":{"moduleName":[],"name":"Err"},"patterns":[{"range":[202,21,202,22],"value":{"type":"all","all":{}}}]}}},"expression":{"range":[203,21,203,83],"value":{"type":"tupled","tupled":[{"range":[203,23,203,71],"value":{"type":"recordUpdate","recordUpdate":{"name":{"range":[203,25,203,30],"value":"model"},"updates":[{"range":[203,33,203,46],"value":{"field":{"range":[203,33,203,37],"value":"page"},"expression":{"range":[203,40,203,46],"value":{"type":"functionOrValue","functionOrValue":{"moduleName":[],"name":"SignIn"}}}}},{"range":[203,48,203,70],"value":{"field":{"range":[203,48,203,59],"value":"userProfile"},"expression":{"range":[203,62,203,69],"value":{"type":"functionOrValue","functionOrValue":{"moduleName":[],"name":"Failure"}}}}}]}}},{"range":[203,73,203,81],"value":{"type":"functionOrValue","functionOrValue":{"moduleName":["Cmd"],"name":"none"}}}]}}}],"expression":{"range":[198,18,198,24],"value":{"type":"functionOrValue","functionOrValue":{"moduleName":[],"name":"result"}}}}}}},{"pattern":{"range":[205,9,205,16],"value":{"type":"named","named":{"qualified":{"moduleName":[],"name":"Profile"},"patterns":[]}}},"expression":{"range":[206,13,206,57],"value":{"type":"tupled","tupled":[{"range":[206,15,206,20],"value":{"type":"functionOrValue","functionOrValue":{"moduleName":[],"name":"model"}}},{"range":[206,22,206,55],"value":{"type":"application","application":[{"range":[206,22,206,38],"value":{"type":"functionOrValue","functionOrValue":{"moduleName":[],"name":"authenticateUser"}}},{"range":[206,44,206,55],"value":{"type":"recordAccess","recordAccess":{"expression":{"range":[206,39,206,44],"value":{"type":"functionOrValue","functionOrValue":{"moduleName":[],"name":"model"}}},"name":{"range":[206,45,206,55],"value":"signinForm"}}}}]}}]}}},{"pattern":{"range":[208,9,208,26],"value":{"type":"named","named":{"qualified":{"moduleName":[],"name":"Username"},"patterns":[{"range":[208,18,208,26],"value":{"type":"var","var":{"value":"username"}}}]}}},"expression":{"range":[209,13,209,89],"value":{"type":"tupled","tupled":[{"range":[209,15,209,77],"value":{"type":"recordUpdate","recordUpdate":{"name":{"range":[209,17,209,22],"value":"model"},"updates":[{"range":[209,25,209,76],"value":{"field":{"range":[209,25,209,35],"value":"signinForm"},"expression":{"range":[209,38,209,75],"value":{"type":"application","application":[{"range":[209,38,209,49],"value":{"type":"functionOrValue","functionOrValue":{"moduleName":[],"name":"newUserName"}}},{"range":[209,50,209,58],"value":{"type":"functionOrValue","functionOrValue":{"moduleName":[],"name":"username"}}},{"range":[209,64,209,75],"value":{"type":"recordAccess","recordAccess":{"expression":{"range":[209,59,209,64],"value":{"type":"functionOrValue","functionOrValue":{"moduleName":[],"name":"model"}}},"name":{"range":[209,65,209,75],"value":"signinForm"}}}}]}}}}]}}},{"range":[209,79,209,87],"value":{"type":"functionOrValue","functionOrValue":{"moduleName":["Cmd"],"name":"none"}}}]}}},{"pattern":{"range":[211,9,211,16],"value":{"type":"named","named":{"qualified":{"moduleName":[],"name":"Pwd"},"patterns":[{"range":[211,13,211,16],"value":{"type":"var","var":{"value":"pwd"}}}]}}},"expression":{"range":[212,13,212,83],"value":{"type":"tupled","tupled":[{"range":[212,15,212,71],"value":{"type":"recordUpdate","recordUpdate":{"name":{"range":[212,17,212,22],"value":"model"},"updates":[{"range":[212,25,212,70],"value":{"field":{"range":[212,25,212,35],"value":"signinForm"},"expression":{"range":[212,38,212,69],"value":{"type":"application","application":[{"range":[212,38,212,48],"value":{"type":"functionOrValue","functionOrValue":{"moduleName":[],"name":"newFormPwd"}}},{"range":[212,49,212,52],"value":{"type":"functionOrValue","functionOrValue":{"moduleName":[],"name":"pwd"}}},{"range":[212,58,212,69],"value":{"type":"recordAccess","recordAccess":{"expression":{"range":[212,53,212,58],"value":{"type":"functionOrValue","functionOrValue":{"moduleName":[],"name":"model"}}},"name":{"range":[212,59,212,69],"value":"signinForm"}}}}]}}}}]}}},{"range":[212,73,212,81],"value":{"type":"functionOrValue","functionOrValue":{"moduleName":["Cmd"],"name":"none"}}}]}}},{"pattern":{"range":[214,9,214,24],"value":{"type":"named","named":{"qualified":{"moduleName":[],"name":"FirstName"},"patterns":[{"range":[214,19,214,24],"value":{"type":"var","var":{"value":"fname"}}}]}}},"expression":{"range":[215,13,215,87],"value":{"type":"tupled","tupled":[{"range":[215,15,215,75],"value":{"type":"recordUpdate","recordUpdate":{"name":{"range":[215,17,215,22],"value":"model"},"updates":[{"range":[215,25,215,74],"value":{"field":{"range":[215,25,215,35],"value":"signupForm"},"expression":{"range":[215,38,215,73],"value":{"type":"application","application":[{"range":[215,38,215,50],"value":{"type":"functionOrValue","functionOrValue":{"moduleName":[],"name":"newFormFName"}}},{"range":[215,51,215,56],"value":{"type":"functionOrValue","functionOrValue":{"moduleName":[],"name":"fname"}}},{"range":[215,62,215,73],"value":{"type":"recordAccess","recordAccess":{"expression":{"range":[215,57,215,62],"value":{"type":"functionOrValue","functionOrValue":{"moduleName":[],"name":"model"}}},"name":{"range":[215,63,215,73],"value":"signupForm"}}}}]}}}}]}}},{"range":[215,77,215,85],"value":{"type":"functionOrValue","functionOrValue":{"moduleName":["Cmd"],"name":"none"}}}]}}},{"pattern":{"range":[217,9,217,23],"value":{"type":"named","named":{"qualified":{"moduleName":[],"name":"LastName"},"patterns":[{"range":[217,18,217,23],"value":{"type":"var","var":{"value":"lname"}}}]}}},"expression":{"range":[218,13,218,87],"value":{"type":"tupled","tupled":[{"range":[218,15,218,75],"value":{"type":"recordUpdate","recordUpdate":{"name":{"range":[218,17,218,22],"value":"model"},"updates":[{"range":[218,25,218,74],"value":{"field":{"range":[218,25,218,35],"value":"signupForm"},"expression":{"range":[218,38,218,73],"value":{"type":"application","application":[{"range":[218,38,218,50],"value":{"type":"functionOrValue","functionOrValue":{"moduleName":[],"name":"newFormLName"}}},{"range":[218,51,218,56],"value":{"type":"functionOrValue","functionOrValue":{"moduleName":[],"name":"lname"}}},{"range":[218,62,218,73],"value":{"type":"recordAccess","recordAccess":{"expression":{"range":[218,57,218,62],"value":{"type":"functionOrValue","functionOrValue":{"moduleName":[],"name":"model"}}},"name":{"range":[218,63,218,73],"value":"signupForm"}}}}]}}}}]}}},{"range":[218,77,218,85],"value":{"type":"functionOrValue","functionOrValue":{"moduleName":["Cmd"],"name":"none"}}}]}}},{"pattern":{"range":[220,9,220,20],"value":{"type":"named","named":{"qualified":{"moduleName":[],"name":"Class"},"patterns":[{"range":[220,15,220,20],"value":{"type":"var","var":{"value":"class"}}}]}}},"expression":{"range":[221,13,221,87],"value":{"type":"tupled","tupled":[{"range":[221,15,221,75],"value":{"type":"recordUpdate","recordUpdate":{"name":{"range":[221,17,221,22],"value":"model"},"updates":[{"range":[221,25,221,74],"value":{"field":{"range":[221,25,221,35],"value":"signupForm"},"expression":{"range":[221,38,221,73],"value":{"type":"application","application":[{"range":[221,38,221,50],"value":{"type":"functionOrValue","functionOrValue":{"moduleName":[],"name":"newFormClass"}}},{"range":[221,51,221,56],"value":{"type":"functionOrValue","functionOrValue":{"moduleName":[],"name":"class"}}},{"range":[221,62,221,73],"value":{"type":"recordAccess","recordAccess":{"expression":{"range":[221,57,221,62],"value":{"type":"functionOrValue","functionOrValue":{"moduleName":[],"name":"model"}}},"name":{"range":[221,63,221,73],"value":"signupForm"}}}}]}}}}]}}},{"range":[221,77,221,85],"value":{"type":"functionOrValue","functionOrValue":{"moduleName":["Cmd"],"name":"none"}}}]}}},{"pattern":{"range":[223,9,223,18],"value":{"type":"named","named":{"qualified":{"moduleName":[],"name":"Mail"},"patterns":[{"range":[223,14,223,18],"value":{"type":"var","var":{"value":"mail"}}}]}}},"expression":{"range":[224,13,224,85],"value":{"type":"tupled","tupled":[{"range":[224,15,224,73],"value":{"type":"recordUpdate","recordUpdate":{"name":{"range":[224,17,224,22],"value":"model"},"updates":[{"range":[224,25,224,72],"value":{"field":{"range":[224,25,224,35],"value":"signupForm"},"expression":{"range":[224,38,224,71],"value":{"type":"application","application":[{"range":[224,38,224,49],"value":{"type":"functionOrValue","functionOrValue":{"moduleName":[],"name":"newFormMail"}}},{"range":[224,50,224,54],"value":{"type":"functionOrValue","functionOrValue":{"moduleName":[],"name":"mail"}}},{"range":[224,60,224,71],"value":{"type":"recordAccess","recordAccess":{"expression":{"range":[224,55,224,60],"value":{"type":"functionOrValue","functionOrValue":{"moduleName":[],"name":"model"}}},"name":{"range":[224,61,224,71],"value":"signupForm"}}}}]}}}}]}}},{"range":[224,75,224,83],"value":{"type":"functionOrValue","functionOrValue":{"moduleName":["Cmd"],"name":"none"}}}]}}}],"expression":{"range":[169,10,169,13],"value":{"type":"functionOrValue","functionOrValue":{"moduleName":[],"name":"msg"}}}}}}}}}}}],"comments":[{"range":[66,1,66,8],"value":"-- VIEW"}]}